django_request_in/__init__.py
django_request_in/decorators.py
django_request_in/fields.py
django_request_in/requests.py
django_request_in/schema_ins.py
django_request_in/validators.py
django_request_in/examples/example_request_in.py
django_request_in/examples/example_request_in_decorator.py
django_request_in-0.0.4.dist-info/METADATA
django_request_in-0.0.4.dist-info/WHEEL
django_request_in-0.0.4.dist-info/top_level.txt
django_request_in-0.0.4.dist-info/RECORD
